faest/__init__.py
faest/__version__.py
faest/_api.py
faest/_auth.py
faest/_client.py
faest/_config.py
faest/_content_streams.py
faest/_decoders.py
faest/_exceptions.py
faest/_models.py
faest/_status_codes.py
faest/_types.py
faest/_utils.py
faest/py.typed
faest/_transports/__init__.py
faest/_transports/asgi.py
faest/_transports/urllib3.py
faest/_transports/wsgi.py
faest-0.14.6.dist-info/LICENSE.md
faest-0.14.6.dist-info/METADATA
faest-0.14.6.dist-info/WHEEL
faest-0.14.6.dist-info/top_level.txt
faest-0.14.6.dist-info/RECORD
