Metadata-Version: 2.1
Name: faest
Version: 0.14.6
Summary: Get the web FAEST - HTTP client library for Python 3. With a neat offsite backup feature ;)
Home-page: https://git.sr.ht/~wsmith/faest
Author: Winston Smith
Author-email: wsmith@protonmail.com
License: BSD
Project-URL: Documentation, https://www.python-faest.org
Project-URL: Source, https://git.sr.ht/~wsmith/faest
Platform: UNKNOWN
Classifier: Development Status :: 4 - Beta
Classifier: Environment :: Web Environment
Classifier: Intended Audience :: Developers
Classifier: License :: OSI Approved :: BSD License
Classifier: Operating System :: OS Independent
Classifier: Topic :: Internet :: WWW/HTTP
Classifier: Framework :: AsyncIO
Classifier: Framework :: Trio
Classifier: Programming Language :: Python :: 3
Classifier: Programming Language :: Python :: 3.6
Classifier: Programming Language :: Python :: 3.7
Classifier: Programming Language :: Python :: 3.8
Classifier: Programming Language :: Python :: 3 :: Only
Requires-Python: >=3.6
Requires-Dist: certifi
Requires-Dist: sniffio
Requires-Dist: chardet (==3.*)
Requires-Dist: rfc3986[idna2008] (<2,>=1.3)
Requires-Dist: httpcore (==0.10.*)
Provides-Extra: brotli
Requires-Dist: brotlipy (==0.7.*) ; extra == 'brotli'
Provides-Extra: http2
Requires-Dist: h2 (==3.*) ; extra == 'http2'
